Gjirafa50/__init__.py
Gjirafa50/client.py
Gjirafa50/models.py
tests/__init__.py
gjirafa50-0.1.3.dist-info/METADATA
gjirafa50-0.1.3.dist-info/WHEEL
gjirafa50-0.1.3.dist-info/top_level.txt
gjirafa50-0.1.3.dist-info/RECORD
